mkrecipe/__init__.py
mkrecipe/__main__.py
mkrecipe/config.py
mkrecipe/py.typed
mkrecipe/recipe_template.ymlt
mkrecipe-0.9.0.dist-info/LICENSE
mkrecipe-0.9.0.dist-info/METADATA
mkrecipe-0.9.0.dist-info/WHEEL
mkrecipe-0.9.0.dist-info/entry_points.txt
mkrecipe-0.9.0.dist-info/RECORD
